nanomd/__init__.py
nanomd/main.py
nanomd/modules/__init__.py
nanomd/modules/count.py
nanomd/modules/detectMod.py
nanomd/modules/gene.py
nanomd/modules/isoformAS.py
nanomd/modules/matrix.py
nanomd/modules/nascentRNA.py
nanomd/modules/ployA.py
nanomd/scripts/gene.R
nanomd/scripts/isoform.R
nanomd/scripts/m6a.sh
nanomd/scripts/metaplot.R
nanomd/scripts/nascentRNA.R
nanomd/scripts/selectM6A.R
nanomd/static/env.yaml
nanomd/utils/__init__.py
nanomd/utils/abs_position.py
nanomd/utils/modifications.py
nanomd/utils/modmutil.py
nanomd/utils/modtools.py
nanomd/utils/nascentRNA_fetch.py
nanomd/utils/ployA_tools.py
nanomd/utils/quantify.py
nanomd/utils/sam_fatures_catch_all.py
nanomd-0.4.8.dist-info/METADATA
nanomd-0.4.8.dist-info/WHEEL
nanomd-0.4.8.dist-info/entry_points.txt
nanomd-0.4.8.dist-info/RECORD
