Metadata-Version: 2.3
Name: nanomd
Version: 0.4.8
Summary: 
Author: DeYing Zhang
Author-email: legendzdy@dingtalk.com
Requires-Python: >=3.10,<4.0
Classifier: Programming Language :: Python :: 3
Classifier: Programming Language :: Python :: 3.10
Classifier: Programming Language :: Python :: 3.11
Classifier: Programming Language :: Python :: 3.12
Classifier: Programming Language :: Python :: 3.13
Requires-Dist: basebio (>=0.4.0)
Requires-Dist: pandas (>=2.3.0)
Requires-Dist: pod5 (>=0.3.28,<0.4.0)
Requires-Dist: pysam (>=0.22.1)
Requires-Dist: scikit-learn (>=1.7.0,<2.0.0)
Requires-Dist: typer (>=0.15.2)
